{
  "kind": "Program",
  "body": [
    {
      "kind": "FunctionDeclaration",
      "name": "sortBy",
      "isExported": true,
      "isDefaultExport": false,
      "isAsync": false,
      "isGenerator": false,
      "typeParameters": [
        {
          "name": "T",
          "constraint": null
        }
      ],
      "returnType": "T[]",
      "parameters": [
        {
          "kind": "Parameter",
          "name": {
            "kind": "Identifier",
            "name": "array",
            "line": 11,
            "column": 27
          },
          "type": "T[]",
          "isOptional": false,
          "isRest": false,
          "initializer": null,
          "access": null,
          "isReadonly": false,
          "isParameterProperty": false,
          "line": 11,
          "column": 27
        },
        {
          "kind": "Parameter",
          "name": {
            "kind": "Identifier",
            "name": "iteratee",
            "line": 11,
            "column": 39
          },
          "type": "(value: T) => number",
          "isOptional": false,
          "isRest": false,
          "initializer": null,
          "access": null,
          "isReadonly": false,
          "isParameterProperty": false,
          "line": 11,
          "column": 39
        }
      ],
      "body": [
        {
          "kind": "VariableDeclaration",
          "name": {
            "kind": "Identifier",
            "name": "result",
            "line": 13,
            "column": 11
          },
          "isExported": false,
          "type": "T[]",
          "initializer": {
            "kind": "ArrayLiteralExpression",
            "elements": [],
            "line": 13,
            "column": 25
          },
          "line": 13,
          "column": 5
        },
        {
          "kind": "VariableDeclaration",
          "name": {
            "kind": "Identifier",
            "name": "i",
            "line": 14,
            "column": 9
          },
          "isExported": false,
          "type": "",
          "initializer": {
            "kind": "NumericLiteral",
            "value": 0,
            "line": 14,
            "column": 13
          },
          "line": 14,
          "column": 5
        },
        {
          "kind": "VariableDeclaration",
          "name": {
            "kind": "Identifier",
            "name": "len",
            "line": 15,
            "column": 11
          },
          "isExported": false,
          "type": "",
          "initializer": {
            "kind": "PropertyAccessExpression",
            "expression": {
              "kind": "Identifier",
              "name": "array",
              "line": 15,
              "column": 17
            },
            "name": "length",
            "isOptional": false,
            "line": 15,
            "column": 17
          },
          "line": 15,
          "column": 5
        },
        {
          "kind": "WhileStatement",
          "condition": {
            "kind": "BinaryExpression",
            "operator": "<",
            "left": {
              "kind": "Identifier",
              "name": "i",
              "line": 16,
              "column": 12
            },
            "right": {
              "kind": "Identifier",
              "name": "len",
              "line": 16,
              "column": 16
            },
            "line": 16,
            "column": 12
          },
          "statement": {
            "kind": "BlockStatement",
            "body": [
              {
                "kind": "ExpressionStatement",
                "expression": {
                  "kind": "CallExpression",
                  "callee": {
                    "kind": "PropertyAccessExpression",
                    "expression": {
                      "kind": "Identifier",
                      "name": "result",
                      "line": 17,
                      "column": 9
                    },
                    "name": "push",
                    "isOptional": false,
                    "line": 17,
                    "column": 9
                  },
                  "arguments": [
                    {
                      "kind": "ElementAccessExpression",
                      "expression": {
                        "kind": "Identifier",
                        "name": "array",
                        "line": 17,
                        "column": 21
                      },
                      "argumentExpression": {
                        "kind": "Identifier",
                        "name": "i",
                        "line": 17,
                        "column": 27
                      },
                      "isOptional": false,
                      "line": 17,
                      "column": 21
                    }
                  ],
                  "typeArguments": [],
                  "isOptional": false,
                  "line": 17,
                  "column": 9
                },
                "line": 17,
                "column": 9
              },
              {
                "kind": "ExpressionStatement",
                "expression": {
                  "kind": "AssignmentExpression",
                  "left": {
                    "kind": "Identifier",
                    "name": "i",
                    "line": 18,
                    "column": 9
                  },
                  "right": {
                    "kind": "BinaryExpression",
                    "operator": "+",
                    "left": {
                      "kind": "Identifier",
                      "name": "i",
                      "line": 18,
                      "column": 13
                    },
                    "right": {
                      "kind": "NumericLiteral",
                      "value": 1,
                      "line": 18,
                      "column": 17
                    },
                    "line": 18,
                    "column": 13
                  },
                  "line": 18,
                  "column": 9
                },
                "line": 18,
                "column": 9
              }
            ],
            "line": 16,
            "column": 21
          },
          "line": 16,
          "column": 5
        },
        {
          "kind": "ExpressionStatement",
          "expression": {
            "kind": "CallExpression",
            "callee": {
              "kind": "PropertyAccessExpression",
              "expression": {
                "kind": "Identifier",
                "name": "result",
                "line": 22,
                "column": 5
              },
              "name": "sort",
              "isOptional": false,
              "line": 22,
              "column": 5
            },
            "arguments": [
              {
                "kind": "ArrowFunction",
                "isAsync": false,
                "parameters": [
                  {
                    "kind": "Parameter",
                    "name": {
                      "kind": "Identifier",
                      "name": "a",
                      "line": 22,
                      "column": 18
                    },
                    "type": "T",
                    "isOptional": false,
                    "isRest": false,
                    "initializer": null,
                    "access": null,
                    "isReadonly": false,
                    "isParameterProperty": false,
                    "line": 22,
                    "column": 18
                  },
                  {
                    "kind": "Parameter",
                    "name": {
                      "kind": "Identifier",
                      "name": "b",
                      "line": 22,
                      "column": 24
                    },
                    "type": "T",
                    "isOptional": false,
                    "isRest": false,
                    "initializer": null,
                    "access": null,
                    "isReadonly": false,
                    "isParameterProperty": false,
                    "line": 22,
                    "column": 24
                  }
                ],
                "body": {
                  "kind": "BlockStatement",
                  "body": [
                    {
                      "kind": "VariableDeclaration",
                      "name": {
                        "kind": "Identifier",
                        "name": "aKey",
                        "line": 23,
                        "column": 15
                      },
                      "isExported": false,
                      "type": "",
                      "initializer": {
                        "kind": "CallExpression",
                        "callee": {
                          "kind": "Identifier",
                          "name": "iteratee",
                          "line": 23,
                          "column": 22
                        },
                        "arguments": [
                          {
                            "kind": "Identifier",
                            "name": "a",
                            "line": 23,
                            "column": 31
                          }
                        ],
                        "typeArguments": [],
                        "isOptional": false,
                        "line": 23,
                        "column": 22
                      },
                      "line": 23,
                      "column": 9
                    },
                    {
                      "kind": "VariableDeclaration",
                      "name": {
                        "kind": "Identifier",
                        "name": "bKey",
                        "line": 24,
                        "column": 15
                      },
                      "isExported": false,
                      "type": "",
                      "initializer": {
                        "kind": "CallExpression",
                        "callee": {
                          "kind": "Identifier",
                          "name": "iteratee",
                          "line": 24,
                          "column": 22
                        },
                        "arguments": [
                          {
                            "kind": "Identifier",
                            "name": "b",
                            "line": 24,
                            "column": 31
                          }
                        ],
                        "typeArguments": [],
                        "isOptional": false,
                        "line": 24,
                        "column": 22
                      },
                      "line": 24,
                      "column": 9
                    },
                    {
                      "kind": "IfStatement",
                      "condition": {
                        "kind": "BinaryExpression",
                        "operator": "<",
                        "left": {
                          "kind": "Identifier",
                          "name": "aKey",
                          "line": 25,
                          "column": 13
                        },
                        "right": {
                          "kind": "Identifier",
                          "name": "bKey",
                          "line": 25,
                          "column": 20
                        },
                        "line": 25,
                        "column": 13
                      },
                      "thenStatement": {
                        "kind": "ReturnStatement",
                        "expression": {
                          "kind": "PrefixUnaryExpression",
                          "operator": "-",
                          "operand": {
                            "kind": "NumericLiteral",
                            "value": 1,
                            "line": 25,
                            "column": 34
                          },
                          "line": 25,
                          "column": 33
                        },
                        "line": 25,
                        "column": 26
                      },
                      "elseStatement": null,
                      "line": 25,
                      "column": 9
                    },
                    {
                      "kind": "IfStatement",
                      "condition": {
                        "kind": "BinaryExpression",
                        "operator": ">",
                        "left": {
                          "kind": "Identifier",
                          "name": "aKey",
                          "line": 26,
                          "column": 13
                        },
                        "right": {
                          "kind": "Identifier",
                          "name": "bKey",
                          "line": 26,
                          "column": 20
                        },
                        "line": 26,
                        "column": 13
                      },
                      "thenStatement": {
                        "kind": "ReturnStatement",
                        "expression": {
                          "kind": "NumericLiteral",
                          "value": 1,
                          "line": 26,
                          "column": 33
                        },
                        "line": 26,
                        "column": 26
                      },
                      "elseStatement": null,
                      "line": 26,
                      "column": 9
                    },
                    {
                      "kind": "ReturnStatement",
                      "expression": {
                        "kind": "NumericLiteral",
                        "value": 0,
                        "line": 27,
                        "column": 16
                      },
                      "line": 27,
                      "column": 9
                    }
                  ],
                  "line": 22,
                  "column": 33
                },
                "line": 22,
                "column": 17
              }
            ],
            "typeArguments": [],
            "isOptional": false,
            "line": 22,
            "column": 5
          },
          "line": 22,
          "column": 5
        },
        {
          "kind": "ReturnStatement",
          "expression": {
            "kind": "Identifier",
            "name": "result",
            "line": 30,
            "column": 12
          },
          "line": 30,
          "column": 5
        }
      ],
      "decorators": [],
      "line": 11,
      "column": 1
    },
    {
      "kind": "FunctionDeclaration",
      "name": "sortByDesc",
      "isExported": true,
      "isDefaultExport": false,
      "isAsync": false,
      "isGenerator": false,
      "typeParameters": [
        {
          "name": "T",
          "constraint": null
        }
      ],
      "returnType": "T[]",
      "parameters": [
        {
          "kind": "Parameter",
          "name": {
            "kind": "Identifier",
            "name": "array",
            "line": 40,
            "column": 31
          },
          "type": "T[]",
          "isOptional": false,
          "isRest": false,
          "initializer": null,
          "access": null,
          "isReadonly": false,
          "isParameterProperty": false,
          "line": 40,
          "column": 31
        },
        {
          "kind": "Parameter",
          "name": {
            "kind": "Identifier",
            "name": "iteratee",
            "line": 40,
            "column": 43
          },
          "type": "(value: T) => number",
          "isOptional": false,
          "isRest": false,
          "initializer": null,
          "access": null,
          "isReadonly": false,
          "isParameterProperty": false,
          "line": 40,
          "column": 43
        }
      ],
      "body": [
        {
          "kind": "VariableDeclaration",
          "name": {
            "kind": "Identifier",
            "name": "result",
            "line": 42,
            "column": 11
          },
          "isExported": false,
          "type": "T[]",
          "initializer": {
            "kind": "ArrayLiteralExpression",
            "elements": [],
            "line": 42,
            "column": 25
          },
          "line": 42,
          "column": 5
        },
        {
          "kind": "VariableDeclaration",
          "name": {
            "kind": "Identifier",
            "name": "i",
            "line": 43,
            "column": 9
          },
          "isExported": false,
          "type": "",
          "initializer": {
            "kind": "NumericLiteral",
            "value": 0,
            "line": 43,
            "column": 13
          },
          "line": 43,
          "column": 5
        },
        {
          "kind": "VariableDeclaration",
          "name": {
            "kind": "Identifier",
            "name": "len",
            "line": 44,
            "column": 11
          },
          "isExported": false,
          "type": "",
          "initializer": {
            "kind": "PropertyAccessExpression",
            "expression": {
              "kind": "Identifier",
              "name": "array",
              "line": 44,
              "column": 17
            },
            "name": "length",
            "isOptional": false,
            "line": 44,
            "column": 17
          },
          "line": 44,
          "column": 5
        },
        {
          "kind": "WhileStatement",
          "condition": {
            "kind": "BinaryExpression",
            "operator": "<",
            "left": {
              "kind": "Identifier",
              "name": "i",
              "line": 45,
              "column": 12
            },
            "right": {
              "kind": "Identifier",
              "name": "len",
              "line": 45,
              "column": 16
            },
            "line": 45,
            "column": 12
          },
          "statement": {
            "kind": "BlockStatement",
            "body": [
              {
                "kind": "ExpressionStatement",
                "expression": {
                  "kind": "CallExpression",
                  "callee": {
                    "kind": "PropertyAccessExpression",
                    "expression": {
                      "kind": "Identifier",
                      "name": "result",
                      "line": 46,
                      "column": 9
                    },
                    "name": "push",
                    "isOptional": false,
                    "line": 46,
                    "column": 9
                  },
                  "arguments": [
                    {
                      "kind": "ElementAccessExpression",
                      "expression": {
                        "kind": "Identifier",
                        "name": "array",
                        "line": 46,
                        "column": 21
                      },
                      "argumentExpression": {
                        "kind": "Identifier",
                        "name": "i",
                        "line": 46,
                        "column": 27
                      },
                      "isOptional": false,
                      "line": 46,
                      "column": 21
                    }
                  ],
                  "typeArguments": [],
                  "isOptional": false,
                  "line": 46,
                  "column": 9
                },
                "line": 46,
                "column": 9
              },
              {
                "kind": "ExpressionStatement",
                "expression": {
                  "kind": "AssignmentExpression",
                  "left": {
                    "kind": "Identifier",
                    "name": "i",
                    "line": 47,
                    "column": 9
                  },
                  "right": {
                    "kind": "BinaryExpression",
                    "operator": "+",
                    "left": {
                      "kind": "Identifier",
                      "name": "i",
                      "line": 47,
                      "column": 13
                    },
                    "right": {
                      "kind": "NumericLiteral",
                      "value": 1,
                      "line": 47,
                      "column": 17
                    },
                    "line": 47,
                    "column": 13
                  },
                  "line": 47,
                  "column": 9
                },
                "line": 47,
                "column": 9
              }
            ],
            "line": 45,
            "column": 21
          },
          "line": 45,
          "column": 5
        },
        {
          "kind": "ExpressionStatement",
          "expression": {
            "kind": "CallExpression",
            "callee": {
              "kind": "PropertyAccessExpression",
              "expression": {
                "kind": "Identifier",
                "name": "result",
                "line": 51,
                "column": 5
              },
              "name": "sort",
              "isOptional": false,
              "line": 51,
              "column": 5
            },
            "arguments": [
              {
                "kind": "ArrowFunction",
                "isAsync": false,
                "parameters": [
                  {
                    "kind": "Parameter",
                    "name": {
                      "kind": "Identifier",
                      "name": "a",
                      "line": 51,
                      "column": 18
                    },
                    "type": "T",
                    "isOptional": false,
                    "isRest": false,
                    "initializer": null,
                    "access": null,
                    "isReadonly": false,
                    "isParameterProperty": false,
                    "line": 51,
                    "column": 18
                  },
                  {
                    "kind": "Parameter",
                    "name": {
                      "kind": "Identifier",
                      "name": "b",
                      "line": 51,
                      "column": 24
                    },
                    "type": "T",
                    "isOptional": false,
                    "isRest": false,
                    "initializer": null,
                    "access": null,
                    "isReadonly": false,
                    "isParameterProperty": false,
                    "line": 51,
                    "column": 24
                  }
                ],
                "body": {
                  "kind": "BlockStatement",
                  "body": [
                    {
                      "kind": "VariableDeclaration",
                      "name": {
                        "kind": "Identifier",
                        "name": "aKey",
                        "line": 52,
                        "column": 15
                      },
                      "isExported": false,
                      "type": "",
                      "initializer": {
                        "kind": "CallExpression",
                        "callee": {
                          "kind": "Identifier",
                          "name": "iteratee",
                          "line": 52,
                          "column": 22
                        },
                        "arguments": [
                          {
                            "kind": "Identifier",
                            "name": "a",
                            "line": 52,
                            "column": 31
                          }
                        ],
                        "typeArguments": [],
                        "isOptional": false,
                        "line": 52,
                        "column": 22
                      },
                      "line": 52,
                      "column": 9
                    },
                    {
                      "kind": "VariableDeclaration",
                      "name": {
                        "kind": "Identifier",
                        "name": "bKey",
                        "line": 53,
                        "column": 15
                      },
                      "isExported": false,
                      "type": "",
                      "initializer": {
                        "kind": "CallExpression",
                        "callee": {
                          "kind": "Identifier",
                          "name": "iteratee",
                          "line": 53,
                          "column": 22
                        },
                        "arguments": [
                          {
                            "kind": "Identifier",
                            "name": "b",
                            "line": 53,
                            "column": 31
                          }
                        ],
                        "typeArguments": [],
                        "isOptional": false,
                        "line": 53,
                        "column": 22
                      },
                      "line": 53,
                      "column": 9
                    },
                    {
                      "kind": "IfStatement",
                      "condition": {
                        "kind": "BinaryExpression",
                        "operator": ">",
                        "left": {
                          "kind": "Identifier",
                          "name": "aKey",
                          "line": 54,
                          "column": 13
                        },
                        "right": {
                          "kind": "Identifier",
                          "name": "bKey",
                          "line": 54,
                          "column": 20
                        },
                        "line": 54,
                        "column": 13
                      },
                      "thenStatement": {
                        "kind": "ReturnStatement",
                        "expression": {
                          "kind": "PrefixUnaryExpression",
                          "operator": "-",
                          "operand": {
                            "kind": "NumericLiteral",
                            "value": 1,
                            "line": 54,
                            "column": 34
                          },
                          "line": 54,
                          "column": 33
                        },
                        "line": 54,
                        "column": 26
                      },
                      "elseStatement": null,
                      "line": 54,
                      "column": 9
                    },
                    {
                      "kind": "IfStatement",
                      "condition": {
                        "kind": "BinaryExpression",
                        "operator": "<",
                        "left": {
                          "kind": "Identifier",
                          "name": "aKey",
                          "line": 55,
                          "column": 13
                        },
                        "right": {
                          "kind": "Identifier",
                          "name": "bKey",
                          "line": 55,
                          "column": 20
                        },
                        "line": 55,
                        "column": 13
                      },
                      "thenStatement": {
                        "kind": "ReturnStatement",
                        "expression": {
                          "kind": "NumericLiteral",
                          "value": 1,
                          "line": 55,
                          "column": 33
                        },
                        "line": 55,
                        "column": 26
                      },
                      "elseStatement": null,
                      "line": 55,
                      "column": 9
                    },
                    {
                      "kind": "ReturnStatement",
                      "expression": {
                        "kind": "NumericLiteral",
                        "value": 0,
                        "line": 56,
                        "column": 16
                      },
                      "line": 56,
                      "column": 9
                    }
                  ],
                  "line": 51,
                  "column": 33
                },
                "line": 51,
                "column": 17
              }
            ],
            "typeArguments": [],
            "isOptional": false,
            "line": 51,
            "column": 5
          },
          "line": 51,
          "column": 5
        },
        {
          "kind": "ReturnStatement",
          "expression": {
            "kind": "Identifier",
            "name": "result",
            "line": 59,
            "column": 12
          },
          "line": 59,
          "column": 5
        }
      ],
      "decorators": [],
      "line": 40,
      "column": 1
    }
  ]
}